{
  "日本": {
    "關東": {
      "東京": [
        "東京鐵塔",
        "東京迪士尼樂園",
        "淺草寺",
        "明治神宮",
        "新宿御苑",
        "上野公園",
        "六本木",
        "秋葉原",
        "銀座",
        "東京晴空塔",
        "淺草",
        "雷門",
        "新宿",
        "銀座",
        "涉谷",
        "原宿",
        "東京"
      ],
      "橫濱": [
        "橫濱中華街",
        "橫濱紅磚倉庫",
        "山下公園",
        "橫濱港未來21",
        "三溪園",
        "橫濱海洋塔",
        "橫濱八景島海島樂園",
        "新橫濱拉麵博物館",
        "港の見える丘公園",
        "日本丸紀念公園",
        "橫濱"
      ],
      "箱根": [
        "蘆之湖",
        "大涌谷",
        "箱根神社",
        "箱根雕刻之森美術館",
        "強羅公園",
        "箱根關所跡",
        "箱根登山鐵道",
        "星之王子博物館",
        "箱根海盜船",
        "小涌園",
        "箱根"
      ],
      "鎌倉": [
        "鎌倉大佛",
        "鶴岡八幡宮",
        "長谷寺",
        "江之島",
        "建長寺",
        "圓覺寺",
        "高德院",
        "報國寺",
        "銭洗弁財天",
        "鎌倉文學館",
        "鎌倉",
        "灌籃高手"
      ],
      "群馬": [
        "草津溫泉",
        "伊香保溫泉",
        "四万溫泉",
        "榛名山",
        "赤城山",
        "群馬縣立自然史博物館",
        "榛名湖",
        "吹割瀑布",
        "老神溫泉",
        "水上溫泉",
        "群馬"
      ]
    },
    "關西": {
      "大阪": [
        "大阪城",
        "心齋橋",
        "道頓堀",
        "黑門市場",
        "環球影城",
        "天王寺動物園",
        "通天閣",
        "梅田藍天大廈",
        "海遊館",
        "天保山摩天輪",
        "大阪"
      ],
      "京都": [
        "清水寺",
        "金閣寺",
        "伏見稻荷大社",
        "嵐山",
        "二條城",
        "銀閣寺",
        "祇園",
        "東福寺",
        "南禪寺",
        "平安神宮",
        "京都"
      ],
      "神戶": [
        "神戶港",
        "六甲山",
        "有馬溫泉",
        "北野異人館",
        "神戶牛肉",
        "明石海峽大橋",
        "神戶市立博物館",
        "摩耶山",
        "神戶動物王國",
        "神戶港塔",
        "神戶",
        "北野"
      ],
      "奈良": [
        "奈良公園",
        "東大寺",
        "春日大社",
        "平城宮跡",
        "興福寺",
        "正倉院",
        "唐招提寺",
        "薬師寺",
        "若草山",
        "法隆寺",
        "奈良"
      ],
      "宇治": [
        "平等院",
        "宇治川",
        "宇治茶",
        "宇治神社",
        "萬福寺",
        "三室戶寺",
        "宇治上神社",
        "宇治市源氏物語博物館",
        "茶室對凄庵",
        "中村藤吉本店",
        "宇治",
        "抹茶"
      ]
    },
    "北海道": {
      "札幌": [
        "札幌電視塔",
        "大通公園",
        "北海道大學",
        "白色戀人公園",
        "藻岩山",
        "札幌啤酒博物館",
        "圓山動物園",
        "北海道廳舊本廳舍",
        "北海道神宮",
        "時計台",
        "札幌",
        "電視台"
      ],
      "小樽": [
        "小樽運河",
        "小樽音樂盒堂",
        "北一硝子",
        "堺町通商店街",
        "小樽市綜合博物館",
        "天狗山",
        "小樽水族館",
        "銭函海水浴場",
        "祝津航路",
        "小樽市歷史建築",
        "小樽"
      ],
      "函館": [
        "函館山",
        "元町",
        "五稜郭",
        "函館朝市",
        "金森紅磚倉庫",
        "函館港",
        "函館教會群",
        "函館市熱帶植物園",
        "函館海洋公園",
        "函館八幡宮",
        "函館"
      ],
      "富良野": [
        "富田農場",
        "美瑛青池",
        "美瑛之丘",
        "富良野葡萄酒工廠",
        "富良野滑雪場",
        "風之花園",
        "四季彩之丘",
        "富良野自然森林",
        "美瑛拼布之路",
        "拓真館"
      ],
      "旭川": [
        "旭山動物園",
        "旭川市博物館",
        "花咲牛",
        "旭川冬季冰雕節",
        "大雪山國立公園",
        "男山酒造資料館",
        "嵐山",
        "旭川市科學館",
        "上川神社",
        "常盤公園",
        "旭川"
      ],
      "登別": [
        "登別地獄谷",
        "登別溫泉",
        "熊牧場",
        "登別尼克斯海洋公園",
        "登別市立雪合戰資料館",
        "大湯沼",
        "伊達時代村",
        "登別原始林",
        "鬼火之路",
        "北海道"
      ]
    },
    "日本-九州": {
      "福岡": [
        "太宰府天滿宮",
        "福岡塔",
        "櫛田神社",
        "博多運河城",
        "福岡城跡",
        "中洲",
        "福岡亞洲美術館",
        "海之中道海浜公園",
        "福岡市動植物園",
        "天神地下街",
        "福岡"
      ],
      "熊本": [
        "熊本城",
        "阿蘇山",
        "水前寺成趣園",
        "熊本熊辦公室",
        "黑川溫泉",
        "阿蘇草千里",
        "阿蘇神社",
        "熊本市現代美術館",
        "熊本縣立美術館",
        "阿蘇火山博物館",
        "熊本"
      ],
      "長崎": [
        "長崎原爆資料館",
        "軍艦島",
        "萬國橋",
        "哥拉巴公園",
        "眼鏡橋",
        "出島",
        "稻佐山",
        "夜景",
        "平和公園",
        "尾曲山展望台",
        "長崎"
      ],
      "大分": [
        "別府地獄溫泉",
        "湯布院",
        "別府海濱沙浴場",
        "由布岳",
        "耶馬溪",
        "高崎山自然動物公園",
        "九重夢大吊橋",
        "寶泉寺",
        "宇佐神宮",
        "臼杵石佛"
      ],
      "別府": [
        "別府八湯",
        "血之池地獄",
        "龍卷地獄",
        "鬼石坊主地獄",
        "白池地獄",
        "海地獄",
        "鬼山地獄",
        "灶地獄",
        "別府纜車",
        "別府公園",
        "別府"
      ],
      "由布院": [
        "金鱗湖",
        "由布岳",
        "湯之坪街道",
        "由布院溫泉",
        "由布院駅",
        "柚之香",
        "岳本公園",
        "湯平溫泉",
        "狹霧台",
        "由布院牧場"
      ]
    },
    "沖繩": {
      "那霸": [
        "首里城",
        "國際通",
        "波上宮",
        "沖繩縣立博物館",
        "玉泉洞",
        "福州園",
        "奧武山公園",
        "那霸市傳統工藝館",
        "識名園",
        "平和祈念公園",
        "那霸"
      ],
      "美國村": [
        "美國村廣場",
        "夕陽海灘",
        "北谷公園",
        "美濱安良波海灘",
        "Depot Island",
        "Mihama 7 Plex",
        "海邊步道",
        "海洋博覽會公園",
        "美國村摩天輪",
        "Aeon Rycom購物中心"
      ],
      "石垣島": [
        "川平灣",
        "石垣島鹿兒島森林",
        "玉取崎展望台",
        "石垣燈塔",
        "米原海灘",
        "平久保崎燈塔",
        "伊原間海灘",
        "バンナ公園",
        "竹富島",
        "西表島",
        "石垣島"
      ],
      "沖繩": [
        "首里城",
        "國際通",
        "JUNGLIA",
        "美麗海水族館",
        "萬座毛",
        "古宇利大橋",
        "沖繩"
      ]
    },
    "東北": {
      "銀山溫泉": [
        "銀山溫泉街",
        "白銀之湯",
        "能登屋旅館",
        "銀山橋",
        "銀山川",
        "銀山風呂",
        "大正浪漫館",
        "銀山公園",
        "銀山神社",
        "白銀公園",
        "銀山"
      ],
      "山形": [
        "山寺",
        "藏王溫泉",
        "羽黑山",
        "月山",
        "山形縣立博物館",
        "山形城跡",
        "上山城",
        "蔵王樹冰",
        "天童",
        "鶴岡",
        "山形"
      ],
      "仙台": [
        "仙台城跡",
        "瑞鳳殿",
        "仙台MediaTheque",
        "仙台市博物館",
        "青葉神社",
        "仙台市天文台",
        "仙台市野生動物園",
        "七夕祭",
        "秋保大瀑布",
        "廣瀨川",
        "仙台"
      ],
      "青森": [
        "青森縣立美術館",
        "三內丸山遺跡",
        "奧入瀨溪流",
        "十和田湖",
        "青森灣",
        "八甲田山",
        "青森之夏祭典",
        "恐山",
        "鶴之舞橋",
        "種差海岸",
        "青森"
      ],
      "秋田": [
        "田澤湖",
        "乳頭溫泉",
        "角館",
        "男鹿半島",
        "秋田縣立美術館",
        "秋田市民俗藝能傳承館",
        "秋田市立赤れんが郷土館",
        "千秋公園",
        "小安峽",
        "鳥海山",
        "秋田"
      ],
      "岩手": [
        "中尊寺",
        "嚴美溪",
        "遠野故鄉村",
        "龍泉洞",
        "小岩井農場",
        "盛岡城跡公園",
        "岩手山",
        "花卷溫泉",
        "龍泉洞",
        "釜石"
      ]
    },
    "新潟": {
      "新潟市": [
        "新潟市水族館",
        "新潟縣政府展望台",
        "白山神社",
        "萬代橋",
        "新潟市美術館",
        "新潟市歴史博物館",
        "新潟市民藝術文化會館",
        "信濃川",
        "新潟港",
        "朱鷺メッセ",
        "新潟"
      ],
      "佐渡島": [
        "佐渡金山",
        "尖閣湾",
        "佐渡國小木民俗博物館",
        "佐渡太鼓體驗交流館",
        "西三河內黃金公園",
        "佐渡歷史傳統館",
        "佐渡能樂之里",
        "矢島經島",
        "佐渡海洋科學館",
        "真野宮"
      ],
      "越後湯沢": [
        "GALA湯沢滑雪場",
        "湯沢高原滑雪場",
        "神立高原滑雪場",
        "越後湯沢溫泉",
        "岩原滑雪場",
        "湯沢中里滑雪場",
        "清津峽",
        "苗場滑雪場",
        "湯沢市街",
        "石打丸山滑雪場"
      ],
      "妙高": [
        "妙高高原池之平",
        "斑尾高原滑雪場",
        "赤倉溫泉滑雪場",
        "妙高溫泉",
        "燕溫泉",
        "關溫泉",
        "妙高山",
        "笹之雪滑雪場",
        "上越國際滑雪場",
        "黑姬高原"
      ]
    },
    "富士山地區": [
      "河口湖",
      "新倉富士淺間神社",
      "富士急樂園",
      "富士五湖",
      "富士"
    ]
  },
  "韓國": {
    "首爾": {
      "首爾": [
        "首爾"
      ],
      "明洞": [
        "明洞聖堂",
        "樂天百貨",
        "明洞地下街",
        "南大門市場",
        "美食街",
        "Line Friends Store",
        "秀泰",
        "樂天免稅店",
        "Olive Young",
        "新世界百貨",
        "明洞"
      ],
      "東大門": [
        "東大門設計廣場",
        "東大門",
        "清溪川",
        "興仁之門",
        "平和市場",
        "東大門運動場",
        "新堂洞摩天輪",
        "東大門歷史文化公園",
        "現代城市購物中心",
        "時尚購物中心",
        "東大門夜市"
      ],
      "弘大": [
        "弘益大學",
        "弘大商圈",
        "弘大地下街",
        "9眼橋",
        "梨花壁畫村",
        "Trick Eye Museum",
        "Kakao Friends Store",
        "塗鴉秀",
        "Club Cocoon",
        "天空公園",
        "弘大"
      ],
      "景福宮": [
        "光化門",
        "景福宮",
        "國立民俗博物館",
        "三清洞",
        "青瓦台",
        "景福宮夜景",
        "光化門廣場",
        "北村韓屋村",
        "仁寺洞",
        "昌德宮"
      ],
      "南山塔": [
        "N首爾塔",
        "愛情鎖牆",
        "南山公園",
        "八角亭",
        "首爾塔廣場",
        "南山纜車",
        "南山展望台",
        "首爾夜景",
        "阿利水",
        "首爾城郭",
        "南山"
      ],
      "梨花女子大學": [
        "梨花校園",
        "梨花壁畫街",
        "梨花藝術館",
        "梨花博物館",
        "梨花校園商店街",
        "梨花校門",
        "ECC文化中心",
        "姬誕生地",
        "梨花園"
      ]
    },
    "釜山": {
      "釜山": [
        "海雲台海灘",
        "甘川洞文化村",
        "釜山塔",
        "太宗台",
        "龍頭山公園",
        "五六島天空步道",
        "札嘎其市場",
        "西面",
        "廣安大橋",
        "釜山水族館",
        "釜山"
      ],
      "海雲台": [
        "海雲台海灘",
        "釜山水族館",
        "海雲台市場",
        "冬柏島",
        "達里公園",
        "釜山電影節廣場",
        "海水浴場",
        "樂天飯店",
        "The Bay 101",
        "海雲台列車站",
        "海雲台"
      ],
      "甘川洞": [
        "甘川洞文化村",
        "彩繪壁畫",
        "小王子像",
        "觀景台",
        "甘川洞博物館",
        "甘川洞咖啡街",
        "甘川2洞",
        "甘川洞天空步道",
        "影子舞步",
        "甘川洞藝術工坊"
      ],
      "龍頭山": [
        "龍頭山公園",
        "釜山塔",
        "釜山港",
        "龍頭山觀景台",
        "釜山大橋",
        "龍頭山燈塔",
        "釜山國際市場",
        "BIFF廣場",
        "札嘎其市場",
        "南浦洞"
      ],
      "松島": [
        "松島海水浴場",
        "松島雲橋",
        "松島天空步道",
        "APEC世峰樓",
        "釜山電影院",
        "松島中央公園",
        "釜山國際會展中心",
        "松島海灘",
        "松島纜車",
        "松島湖"
      ]
    },
    "濟州": {
      "濟州島": [
        "城山日出峰",
        "漢拏山",
        "天帝淵瀑布",
        "泰迪熊博物館",
        "濟州民俗村",
        "龍頭岩",
        "萬丈窟",
        "翰林公園",
        "牛島",
        "濟州植物園"
      ],
      "城山日出峰": [
        "城山日出峰觀景台",
        "城山港",
        "城山浦口",
        "海女博物館",
        "城山海岸",
        "城山日出峰登山口",
        "萬丈窟",
        "城山文化財團地",
        "城山高爾夫球場",
        "城山海水浴場"
      ],
      "漢拏山": [
        "漢拏山國立公園",
        "漢拏山",
        "白鹿潭",
        "觀音寺",
        "靈室",
        "萬里桃園",
        "御里牧",
        "翔鸞峰",
        "漢拏樹木園",
        "韓拏山生態探訪路",
        "登山路線"
      ],
      "天帝淵瀑布": [
        "天帝淵瀑布",
        "天帝淵橋",
        "天帝淵公園",
        "天帝淵步道",
        "天帝淵吊橋",
        "天帝淵水車",
        "天帝淵咖啡館",
        "紅帽子橋",
        "天地淵瀑布文化館",
        "天帝淵生態園"
      ]
    },
    "慶州": [
      "佛國寺",
      "石窟庵",
      "瞻星台",
      "安東河回村"
    ],
    "全州": [
      "全州韓屋村",
      "慶基殿",
      "全州傳統酒博物館"
    ]
  },
  "美國": {
    "紐約": [
      "自由女神像",
      "中央公園",
      "帝國大廈",
      "時代廣場",
      "大都會藝術博物館",
      "百老匯劇院"
    ],
    "洛杉磯": [
      "好萊塢星光大道",
      "環球影城",
      "格里菲斯天文台",
      "比佛利山莊",
      "聖塔莫尼卡海灘",
      "洛杉磯"
    ],
    "舊金山": [
      "金門大橋",
      "漁人碼頭",
      "九曲花街",
      "惡魔島",
      "聯合廣場",
      "舊金山"
    ],
    "拉斯維加斯": [
      "拉斯維加斯大道",
      "百樂宮酒店",
      "威尼斯人酒店",
      "凱撒宮",
      "拉斯維加斯摩天輪",
      "拉斯維加斯"
    ],
    "芝加哥": [
      "千禧公園",
      "雲門（豆子雕塑）",
      "芝加哥藝術博物館",
      "海軍碼頭",
      "威利斯大廈",
      "芝加哥"
    ],
    "華盛頓特區": [
      "白宮",
      "國會大廈",
      "林肯紀念堂",
      "史密森尼博物館群",
      "國家廣場",
      "華盛頓"
    ],
    "奧蘭多": [
      "迪士尼世界",
      "環球影城",
      "海洋世界",
      "奧蘭多科學中心",
      "奧蘭多"
    ]
  },
  "泰國": {
    "曼谷": [
      "大皇宮",
      "玉佛寺",
      "臥佛寺",
      "鄭王廟",
      "恰圖恰克市集",
      "考山路"
    ],
    "清邁": [
      "帕辛寺",
      "素帖寺",
      "清邁夜市",
      "清邁古城",
      "寧曼路"
    ],
    "清萊": [
      "白廟",
      "黑屋博物館",
      "藍廟",
      "金三角地區"
    ],
    "普吉島": [
      "芭東海灘",
      "卡塔海灘",
      "普吉老鎮",
      "普吉大佛",
      "攀牙灣"
    ],
    "蘇美島": [
      "查汶海灘",
      "拉邁海灘",
      "大佛寺",
      "納通鎮",
      "安通國家海洋公園"
    ],
    "華欣": [
      "華欣海灘",
      "華欣夜市",
      "拷汪宮",
      "華欣火車站"
    ]
  },
  "北部": {
    "臺北市": [
      "臺北101",
      "信義商圈",
      "士林夜市",
      "西門町",
      "大安森林公園",
      "陽明山",
      "國立故宮博物院",
      "龍山寺",
      "饒河街夜市",
      "北投溫泉",
      "臺北",
      "台北"
    ],
    "新北市": [
      "九份",
      "平溪",
      "烏來",
      "淡水",
      "三峽老街",
      "野柳地質公園",
      "十分瀑布",
      "鶯歌陶瓷老街",
      "深坑老街",
      "八里左岸",
      "新北"
    ],
    "桃園市": [
      "大溪老街",
      "小烏來",
      "拉拉山",
      "石門水庫",
      "桃園觀音海水浴場",
      "復興角板山",
      "龍潭大池",
      "六福村主題樂園",
      "小人國主題樂園",
      "桃園農業博覽會",
      "桃園"
    ],
    "基隆市": [
      "基隆夜市",
      "和平島",
      "八斗子",
      "象鼻岩",
      "基隆廟口",
      "望幽谷",
      "海洋科技博物館",
      "中正公園",
      "情人湖",
      "二沙灣砲台",
      "基隆",
      "第二人6折｜基隆旅遊｜贈人氣芋泥球！最新地標基隆塔.太平青鳥書店.老鷹岩步道.仁愛市場大啖美食1日｜大人囝仔"
    ],
    "新竹市": [
      "城隍廟",
      "十八尖山",
      "南寮漁港",
      "新竹公園",
      "玻璃工藝博物館",
      "清華大學",
      "新竹科學園區",
      "青草湖",
      "新竹市立動物園",
      "香山濕地",
      "新竹"
    ],
    "新竹縣": [
      "內灣老街",
      "內灣",
      "六福村",
      "北埔老街",
      "小人國",
      "新埔花園",
      "關西農場",
      "峨眉湖",
      "新豐紅樹林",
      "獅頭山",
      "青蛙石天空步道"
    ],
    "宜蘭縣": [
      "太平山",
      "羅東夜市",
      "冬山河親水公園",
      "蘭陽博物館",
      "龜山島",
      "礁溪溫泉",
      "傳統藝術中心",
      "幾米公園",
      "頭城海水浴場",
      "梅花湖",
      "宜蘭"
    ]
  },
  "中部": {
    "臺中市": [
      "逢甲夜市",
      "高美濕地",
      "高美",
      "東海大學",
      "臺中國家歌劇院",
      "彩虹眷村",
      "勤美",
      "審計新村",
      "新社花海",
      "麗寶樂園",
      "麗寶",
      "大坑步道",
      "中興大學",
      "后豐鐵馬道",
      "臺中",
      "台中"
    ],
    "苗栗縣": [
      "三義木雕",
      "三義",
      "苗栗客家文化園區",
      "泰安溫泉",
      "泰安",
      "南庄老街",
      "獅頭山",
      "通霄神社",
      "飛牛牧場",
      "西湖",
      "西湖渡假村",
      "功維敘隧道",
      "龍騰斷橋",
      "苗栗"
    ],
    "彰化縣": [
      "鹿港老街",
      "鹿港",
      "八卦山",
      "彰化八卦山",
      "田尾公路花園",
      "溪湖糖廠",
      "王功漁港",
      "彰化扇形車庫",
      "扇形車庫",
      "員林進士牌樓",
      "百果山",
      "芬園花卉休憩園區",
      "二水自行車道",
      "彰化"
    ],
    "南投縣": [
      "日月潭",
      "清境農場",
      "九族文化村",
      "九族",
      "溪頭自然教育園區",
      "合歡山",
      "杉林溪",
      "埔里酒廠",
      "集集火車站",
      "魚池日月老茶廠",
      "猴探井天梯"
    ],
    "雲林縣": [
      "劍湖山",
      "古坑綠色隧道",
      "北港朝天宮",
      "雲林農業博覽會",
      "虎尾",
      "口湖遊客中心",
      "蔦松藝術村",
      "土庫老街",
      "樟湖生態中心",
      "西螺大橋",
      "雲林"
    ]
  },
  "南部": {
    "臺南市": [
      "安平古堡",
      "赤崁樓",
      "奇美博物館",
      "台南孔廟",
      "孔廟",
      "四草綠色隧道",
      "七股鹽山",
      "藍晒圖",
      "台南美術館",
      "林百貨",
      "安平老街",
      "奇美",
      "臺南"
    ],
    "高雄市": [
      "旗津",
      "西子灣",
      "愛河",
      "六合夜市",
      "駁二藝術特區",
      "高雄85大樓",
      "佛光山",
      "蓮池潭",
      "旗山老街",
      "義大世界",
      "高雄",
      "義大"
    ],
    "屏東縣": [
      "墾丁",
      "鵝鑾鼻燈塔",
      "國立海洋生物博物館",
      "琉球嶼",
      "大鵬灣",
      "東港漁港",
      "恆春古城",
      "萬巒豬腳",
      "車城福安宮",
      "四重溪溫泉",
      "屏東"
    ],
    "嘉義市": [
      "嘉義公園",
      "嘉義城隍廟",
      "嘉義文化創意產業園區",
      "嘉義鐵道藝術村",
      "鐵道藝術村",
      "北門驛",
      "檜意森活村",
      "射日塔",
      "嘉義植物園",
      "民雄鬼屋",
      "香湖公園",
      "嘉義"
    ],
    "嘉義縣": [
      "阿里山",
      "奮起湖",
      "太平雲梯",
      "梅山太平老街",
      "竹崎公園",
      "新港奉天宮",
      "小笠原山觀景台",
      "蘭潭水庫",
      "布袋高跟鞋教堂",
      "好美里彩繪村"
    ]
  },
  "東部": {
    "花蓮縣": [
      "太魯閣國家公園",
      "七星潭",
      "清水斷崖",
      "花蓮東大門夜市",
      "瑞穗牧場",
      "鯉魚潭",
      "六十石山",
      "花蓮港",
      "林田山林業文化園區",
      "花蓮石雕博物館",
      "花蓮"
    ],
    "臺東縣": [
      "三仙台",
      "鹿野高台",
      "知本溫泉",
      "綠島",
      "池上稻田",
      "台東森林公園",
      "卑南遺址",
      "台東史前博物館",
      "金剛大道",
      "都蘭糖廠",
      "臺東"
    ],
    "宜蘭縣": [
      "太平山",
      "羅東夜市",
      "冬山河親水公園",
      "蘭陽博物館",
      "龜山島",
      "礁溪溫泉",
      "傳統藝術中心",
      "幾米公園",
      "頭城海水浴場",
      "梅花湖",
      "宜蘭"
    ]
  },
  "離島": {
    "澎湖縣": [
      "跨海大橋",
      "七美島",
      "望安島",
      "吉貝島",
      "澎湖水族館",
      "澎湖",
      "澎湖玄武岩",
      "雙心石滬",
      "澎湖天后宮",
      "菊島之星",
      "風櫃聽濤"
    ],
    "金門縣": [
      "金門國家公園",
      "太武山",
      "莒光樓",
      "翟山坑道",
      "金門高粱酒廠",
      "金門高粱",
      "金門",
      "山后民俗文化村",
      "陳景蘭洋樓",
      "榕園",
      "獅山砲陣地",
      "風獅爺"
    ],
    "連江縣": [
      "北竿",
      "南竿",
      "東莒",
      "西莒",
      "馬祖酒廠",
      "連江",
      "北海坑道",
      "芹壁村",
      "東莒燈塔",
      "馬祖大橋",
      "媽祖巨神像"
    ],
    "小琉球": [
      "花瓶岩",
      "美人洞",
      "蛤板灣",
      "烏鬼洞",
      "小琉球",
      "大福漁港",
      "威尼斯沙灘",
      "杉福生態廊道",
      "白燈塔",
      "龍蝦洞",
      "厚石群礁"
    ],
    "綠島": [
      "綠島燈塔",
      "朝日溫泉",
      "綠島",
      "哈巴狗與睡美人岩",
      "綠島監獄",
      "海底溫泉",
      "石朗潛水區",
      "綠島人權文化園區",
      "觀音洞",
      "綠島大白沙",
      "孔子岩"
    ]
  },
  "歐洲": {
    "法國": [
      "巴黎",
      "羅浮宮",
      "凡爾賽",
      "尼斯",
      "馬賽",
      "里昂",
      "法國",
      "英法",
      "香榭麗舍",
      "埃菲爾鐵塔",
      "英荷比法",
      "德瑞法"
    ],
    "義大利": [
      "羅馬",
      "佛羅倫斯",
      "威尼斯",
      "米蘭",
      "拿坡里",
      "義大利"
    ],
    "英國": [
      "倫敦",
      "愛丁堡",
      "曼徹斯特",
      "劍橋",
      "牛津",
      "英國",
      "巨石陣",
      "歐洲之星",
      "英國皇室",
      "巴斯",
      "大英博物館",
      "白金漢宮",
      "溫莎城堡"
    ],
    "荷蘭": [
      "荷蘭",
      "阿姆斯特丹",
      "羊角村",
      "風車村",
      "庫肯霍夫"
    ],
    "歐洲-比利時": [
      "比利時",
      "布魯塞爾",
      "撒尿小童",
      "根特",
      "布魯日"
    ],
    "西班牙": [
      "馬德里",
      "巴塞隆納",
      "塞維亞",
      "格拉納達",
      "馬拉加",
      "西班牙"
    ],
    "土耳其": [
      "土耳其",
      "伊斯坦堡",
      "小番紅花城",
      "卡帕多奇亞",
      "棉花堡",
      "博斯普魯斯"
    ],
    "挪威": [
      "挪威",
      "峽灣",
      "奧斯陸",
      "卑爾根",
      "特羅姆瑟"
    ],
    "瑞士": [
      "瑞士",
      "少女峰",
      "德瑞",
      "馬特宏峰",
      "國王湖",
      "琉森",
      "策馬特",
      "萊茵河"
    ],
    "瑞典": [
      "瑞典",
      "斯德哥爾摩",
      "哥德堡",
      "馬爾默"
    ],
    "芬蘭": [
      "芬蘭",
      "赫爾辛基",
      "羅瓦涅米",
      "阿拉斯加"
    ],
    "丹麥": [
      "丹麥",
      "哥本哈根"
    ],
    "冰島": [
      "冰島",
      "雷克雅維克",
      "藍湖",
      "黃金圈",
      "冰洞",
      "火山"
    ],
    "德國": [
      "柏林",
      "慕尼黑",
      "法蘭克福",
      "科隆",
      "漢堡",
      "德國",
      "啤酒節",
      "科隆大教堂",
      "天鵝堡",
      "羅曼蒂克大道"
    ],
    "奧地利": [
      "奧地利",
      "奧捷",
      "哈修塔特",
      "維也納",
      "薩爾茨堡",
      "哈爾斯塔特"
    ],
    "捷克": [
      "庫倫洛夫",
      "捷克",
      "布拉格",
      "卡爾斯坦因",
      "克魯姆洛夫",
      "聖維特大教堂",
      "查理大橋"
    ],
    "匈牙利": [
      "匈牙利",
      "布達佩斯",
      "多瑙河",
      "馬提亞斯教堂"
    ],
    "歐洲": [
      "歐洲"
    ],
    "埃及": [
      "埃及",
      "開羅",
      "金字塔",
      "阿布辛貝",
      "尼羅河",
      "紅海"
    ]
  },
  "印度": [
    "印度",
    "德里",
    "新德里",
    "孟買",
    "阿格拉",
    "泰姬瑪哈",
    "捷普",
    "齋浦爾",
    "瓦拉納西",
    "瑜珈",
    "恆河"
  ],
  "中國": {
    "北京": [
      "天安門廣場",
      "故宮",
      "長城",
      "頤和園",
      "天壇",
      "什剎海",
      "北京動物園",
      "798藝術區",
      "國家大劇院",
      "清華大學"
    ],
    "上海": [
      "外灘",
      "東方明珠",
      "上海迪士尼",
      "南京路步行街",
      "田子坊",
      "豫園",
      "新天地",
      "上海博物館",
      "靜安寺",
      "徐家匯"
    ],
    "西安": [
      "兵馬俑",
      "大雁塔",
      "西安城牆",
      "鐘樓",
      "回民街",
      "華清池",
      "碑林博物館",
      "大唐不夜城",
      "永興坊",
      "秦始皇陵"
    ],
    "成都": [
      "熊貓基地",
      "寬窄巷子",
      "錦里古街",
      "武侯祠",
      "杜甫草堂",
      "春熙路",
      "青城山",
      "都江堰",
      "文殊院",
      "望江樓"
    ],
    "張家界": [
      "張家界國家森林公園",
      "天門山",
      "玻璃棧道",
      "黃龍洞",
      "寶峰湖",
      "金鞭溪",
      "大峽谷玻璃橋",
      "武陵源",
      "十里畫廊",
      "天子山"
    ],
    "桂林": [
      "象鼻山",
      "漓江",
      "兩江四湖",
      "陽朔西街",
      "銀子岩",
      "七星公園",
      "龍脊梯田",
      "世外桃源",
      "冠岩",
      "遇龍河"
    ],
    "雲南": {
      "麗江": [
        "麗江古城",
        "玉龍雪山",
        "黑龍潭",
        "束河古鎮",
        "木府",
        "白沙古鎮",
        "虎跳峽",
        "玉水寨",
        "長江第一灣",
        "東巴萬神園"
      ],
      "大理": [
        "大理古城",
        "洱海",
        "蒼山",
        "崇聖寺三塔",
        "雙廊",
        "喜洲古鎮",
        "蝴蝶泉",
        "南詔風情島",
        "天龍八部影城",
        "周城"
      ]
    }
  },
  "中國-港澳": {
    "香港": [
      "香港迪士尼樂園",
      "太平山",
      "香港",
      "維多利亞港",
      "星光大道",
      "中環摩天輪",
      "金紫荊廣場",
      "尖沙咀",
      "海洋公園",
      "蘭桂坊",
      "天星小輪"
    ],
    "澳門": [
      "大三巴牌坊",
      "澳門旅遊塔",
      "澳門",
      "威尼斯人度假村",
      "媽閣廟",
      "新葡京",
      "澳門博物館",
      "議事亭前地",
      "澳門漁人碼頭",
      "澳門科學館",
      "路氹金光大道"
    ]
  },
  "東南亞-越南": {
    "河內": [
      "還劍湖",
      "文廟",
      "36古街",
      "巴亭廣場",
      "胡志明紀念館",
      "西湖",
      "鎮國寺",
      "河內大教堂",
      "越南博物館",
      "歌劇院"
    ],
    "胡志明市": [
      "范五老街",
      "西貢大教堂",
      "統一宮",
      "戰爭遺跡博物館",
      "中央郵政局",
      "濱城市場",
      "美術館",
      "湄公河",
      "古芝地道",
      "范老五街"
    ],
    "下龍灣": [
      "下龍灣郵輪",
      "石灰岩島嶼",
      "天堂洞",
      "驚訝洞",
      "迷宮洞",
      "斗雞石",
      "下龍灣夜市",
      "水上活動",
      "海上村落",
      "下龍公園"
    ]
  },
  "東南亞-新加坡": {
    "新加坡": [
      "濱海灣花園",
      "聖淘沙",
      "魚尾獅公園",
      "濱海藝術中心",
      "小印度",
      "牛車水",
      "克拉碼頭",
      "新加坡摩天輪",
      "新加坡",
      "新加坡動物園",
      "裕廊飛禽公園"
    ]
  },
  "東南亞-馬來西亞": {
    "吉隆坡": [
      "雙子星塔",
      "吉隆坡塔",
      "茨廠街",
      "蘇丹阿都沙末大廈",
      "國家清真寺",
      "國家博物館",
      "黑風洞",
      "吉隆坡城市畫廊",
      "吉隆坡",
      "吉隆坡鳥園",
      "國家皇宮"
    ],
    "馬六甲": [
      "荷蘭紅屋",
      "聖保羅山",
      "馬六甲海峽清真寺",
      "海峽清真寺",
      "雞場街",
      "葡萄牙廣場",
      "馬六甲旋轉塔",
      "馬六甲",
      "馬六甲河遊船",
      "青雲亭",
      "博物館群",
      "馬六甲海事博物館"
    ],
    "檳城": [
      "喬治市",
      "升旗山",
      "極樂寺",
      "藍屋",
      "張弼士故居",
      "街頭壁畫",
      "觀音亭",
      "蝴蝶公園",
      "檳城大橋",
      "熱帶香料園"
    ]
  }
}